piwik_pro_mcp/__init__.py
piwik_pro_mcp/api/__init__.py
piwik_pro_mcp/api/auth.py
piwik_pro_mcp/api/client.py
piwik_pro_mcp/api/config.py
piwik_pro_mcp/api/exceptions.py
piwik_pro_mcp/api/methods/__init__.py
piwik_pro_mcp/api/methods/analytics/__init__.py
piwik_pro_mcp/api/methods/analytics/api.py
piwik_pro_mcp/api/methods/analytics/models.py
piwik_pro_mcp/api/methods/apps/__init__.py
piwik_pro_mcp/api/methods/apps/api.py
piwik_pro_mcp/api/methods/apps/models.py
piwik_pro_mcp/api/methods/cdp/__init__.py
piwik_pro_mcp/api/methods/cdp/api.py
piwik_pro_mcp/api/methods/cdp/models.py
piwik_pro_mcp/api/methods/common.py
piwik_pro_mcp/api/methods/container_settings/__init__.py
piwik_pro_mcp/api/methods/container_settings/api.py
piwik_pro_mcp/api/methods/container_settings/models.py
piwik_pro_mcp/api/methods/tag_manager/__init__.py
piwik_pro_mcp/api/methods/tag_manager/api.py
piwik_pro_mcp/api/methods/tag_manager/models.py
piwik_pro_mcp/api/methods/tracker_settings/__init__.py
piwik_pro_mcp/api/methods/tracker_settings/api.py
piwik_pro_mcp/api/methods/tracker_settings/models.py
piwik_pro_mcp/assets/TAG_ASSETS.md
piwik_pro_mcp/assets/tag_manager/tags/custom_tag.json
piwik_pro_mcp/assets/tag_manager/tags/piwik_event.json
piwik_pro_mcp/assets/tag_manager/triggers/click.json
piwik_pro_mcp/assets/tag_manager/triggers/event.json
piwik_pro_mcp/assets/tag_manager/triggers/page_view.json
piwik_pro_mcp/assets/tag_manager/variables/constant.json
piwik_pro_mcp/assets/tag_manager/variables/custom_javascript.json
piwik_pro_mcp/assets/tag_manager/variables/data_layer.json
piwik_pro_mcp/assets/tag_manager/variables/dom_element.json
piwik_pro_mcp/common/__init__.py
piwik_pro_mcp/common/settings.py
piwik_pro_mcp/common/telemetry.py
piwik_pro_mcp/common/templates.py
piwik_pro_mcp/common/tool_schemas.py
piwik_pro_mcp/common/utils.py
piwik_pro_mcp/responses.py
piwik_pro_mcp/server.py
piwik_pro_mcp/tests/__init__.py
piwik_pro_mcp/tests/api/test_client.py
piwik_pro_mcp-0.2.2.dist-info/WHEEL
piwik_pro_mcp-0.2.2.dist-info/entry_points.txt
piwik_pro_mcp-0.2.2.dist-info/METADATA
piwik_pro_mcp-0.2.2.dist-info/RECORD
