Metadata-Version: 2.3
Name: piwik-pro-mcp
Version: 0.2.2
Summary: Piwik PRO MCP server
Keywords: mcp,piwik-pro,analytics,tag manager,piwik,piwik pro,piwik pro analytics
Author: Jarosław Zywert
Author-email: Jarosław Zywert <j.zywert@piwik.pro>
License: MIT
Classifier: Development Status :: 3 - Alpha
Classifier: Intended Audience :: Developers
Classifier: License :: OSI Approved :: MIT License
Classifier: Programming Language :: Python :: 3
Classifier: Programming Language :: Python :: 3.12
Classifier: Programming Language :: Python :: 3.13
Classifier: Topic :: Software Development :: Libraries :: Python Modules
Classifier: Topic :: Internet :: WWW/HTTP :: Dynamic Content
Requires-Dist: mcp[cli]
Requires-Dist: requests>=2.25.0
Requires-Dist: urllib3>=2.5.0
Requires-Dist: pydantic>=2.7.2
Requires-Dist: python-dotenv>=1.1.0
Requires-Dist: httpx>=0.27.0
Requires-Python: >=3.12
Project-URL: Homepage, https://github.com/PiwikPRO/mcp
Project-URL: Issues, https://github.com/PiwikPRO/mcp/issues
Project-URL: Repository, https://github.com/PiwikPRO/mcp
